sparta/tiktokapi/__init__.py
sparta/tiktokapi/access.py
sparta/tiktokapi/models/__init__.py
sparta/tiktokapi/models/constants.py
sparta/tiktokapi/models/model.py
sparta/tiktokapi/py.typed
sparta/tiktokapi/users/__init__.py
sparta/tiktokapi/users/user.py
sparta/tiktokapi/users/videos.py
sparta/tiktokapi/videos/__init__.py
sparta/tiktokapi/videos/videos.py
sparta_tiktokapi-0.1.1.dist-info/LICENSE
sparta_tiktokapi-0.1.1.dist-info/METADATA
sparta_tiktokapi-0.1.1.dist-info/WHEEL
sparta_tiktokapi-0.1.1.dist-info/RECORD
