Metadata-Version: 2.1
Name: sparta-tiktokapi
Version: 0.1.1
Summary: 
Author: Andreas Neumeier
Author-email: andreas.neumeier@unibw.de
Requires-Python: >=3.10.12,<4.0.0
Classifier: Programming Language :: Python :: 3
Classifier: Programming Language :: Python :: 3.11
Classifier: Programming Language :: Python :: 3.12
Requires-Dist: aiohttp (>=3.9.5,<4.0.0)
Requires-Dist: asyncio (>=3.4.3,<4.0.0)
Requires-Dist: pydantic (>=2.8.2,<3.0.0)
Requires-Dist: requests (>=2.32.2,<3.0.0)
